humbldata/__init__.py
humbldata/cli.py
humbldata/py.typed
humbldata/core/__init__.py
humbldata/core/standard_models/__init__.py
humbldata/core/standard_models/abstract/__init__.py
humbldata/core/standard_models/abstract/chart.py
humbldata/core/standard_models/abstract/data.py
humbldata/core/standard_models/abstract/errors.py
humbldata/core/standard_models/abstract/humblobject.py
humbldata/core/standard_models/abstract/query_params.py
humbldata/core/standard_models/abstract/singleton.py
humbldata/core/standard_models/abstract/tagged.py
humbldata/core/standard_models/abstract/warnings.py
humbldata/core/standard_models/openbbapi/EconomyCompositeLeadingIndicatorQueryParams.py
humbldata/core/standard_models/openbbapi/EconomyConsumerPriceIndexQueryParams.py
humbldata/core/standard_models/openbbapi/EquityPriceHistoricalQueryParams.py
humbldata/core/standard_models/openbbapi/EquityPriceQuoteQueryParams.py
humbldata/core/standard_models/openbbapi/EquityProfileQueryParams.py
humbldata/core/standard_models/openbbapi/EtfInfoQueryParams.py
humbldata/core/standard_models/portfolio/__init__.py
humbldata/core/standard_models/portfolio/analytics/__init__.py
humbldata/core/standard_models/portfolio/analytics/etf_category.py
humbldata/core/standard_models/portfolio/analytics/watchlist_table.py
humbldata/core/standard_models/toolbox/__init__.py
humbldata/core/standard_models/toolbox/fundamental/__init__.py
humbldata/core/standard_models/toolbox/fundamental/humbl_compass.py
humbldata/core/standard_models/toolbox/fundamental/humbl_compass_backtest.py
humbldata/core/standard_models/toolbox/technical/__init__.py
humbldata/core/standard_models/toolbox/technical/humbl_channel.py
humbldata/core/standard_models/toolbox/technical/humbl_momentum.py
humbldata/core/standard_models/toolbox/technical/humbl_signal.py
humbldata/core/standard_models/toolbox/technical/realized_volatility.py
humbldata/core/utils/__init__.py
humbldata/core/utils/cache.py
humbldata/core/utils/constants.py
humbldata-1.23.0.dist-info/METADATA
humbldata-1.23.0.dist-info/WHEEL
humbldata-1.23.0.dist-info/licenses/LICENSE
humbldata-1.23.0.dist-info/RECORD
