Metadata-Version: 2.4
Name: humbldata
Version: 1.23.0
Summary: open-sourcing the math behind major financial institutional investors/banks. this package connects financial data analysis to the humblFINANCE website.
Author-email: jenningsFantini <jenningsfantini+github@gmail.com>
License-File: LICENSE
Requires-Python: <3.13,>=3.11
Requires-Dist: aiocache>=0.12.3
Requires-Dist: aiohttp>=3.11.18
Requires-Dist: coloredlogs>=15.0.1
Requires-Dist: dotenv>=0.9.9
Requires-Dist: limits>=5.2.0
Requires-Dist: multidict>=6.4.3
Requires-Dist: numpy>=2.2.5
Requires-Dist: pandas>=2.2.3
Requires-Dist: pandera>=0.23.1
Requires-Dist: plotly>=6.0.1
Requires-Dist: polars>=1.29.0
Requires-Dist: pyarrow>=20.0.0
Requires-Dist: pydantic>=2.11.4
Requires-Dist: python-redis-cache>=4.0.2
Requires-Dist: uuid7>=0.1.0
Requires-Dist: uvloop>=0.21.0
